PMMatomo
