Metadata-Version: 2.1
Name: PMMatomo
Version: 0.0.5
Summary: A Python wrapper for the Matomo HTTP reporting API.
Home-page: https://github.com/philippmayrth/PMMatomo
Author: Philipp Mayr
Author-email: me@philipp-mayr.de
License: MIT
Platform: UNKNOWN
Classifier: Programming Language :: Python :: 3
Classifier: Operating System :: OS Independent
Classifier: Topic :: Office/Business
Classifier: Topic :: Office/Business :: Financial :: Investment
